pyspyke/__init__.py
pyspyke/pyspyke.py
pyspyke-0.0.2.dist-info/METADATA
pyspyke-0.0.2.dist-info/WHEEL
pyspyke-0.0.2.dist-info/entry_points.txt
pyspyke-0.0.2.dist-info/top_level.txt
pyspyke-0.0.2.dist-info/RECORD
